jac_splice_orc/__init__.py
jac_splice_orc/config/__init__.py
jac_splice_orc/config/config.json
jac_splice_orc/config/config_loader.py
jac_splice_orc/grpc_local/__init__.py
jac_splice_orc/managers/__init__.py
jac_splice_orc/managers/pod_manager.py
jac_splice_orc/managers/proxy_manager.py
jac_splice_orc/plugin/__init__.py
jac_splice_orc/plugin/splice_plugin.py
jac_splice_orc/server/__init__.py
jac_splice_orc/server/server.py
jac_splice_orc/test/__init__.py
jac_splice_orc/test/test_pod_manager.py
jac_splice_orc/utils/__init__.py
jac_splice_orc-0.1.8.dist-info/METADATA
jac_splice_orc-0.1.8.dist-info/WHEEL
jac_splice_orc-0.1.8.dist-info/entry_points.txt
jac_splice_orc-0.1.8.dist-info/top_level.txt
jac_splice_orc-0.1.8.dist-info/RECORD
