Metadata-Version: 2.1
Name: jac-splice-orc
Version: 0.1.8
Summary: JAC Splice-Orchestrator: Kubernetes-based dynamic remote module management for JacLang
Author: Jason Mars
Author-email: jason@jaseci.org
Classifier: Programming Language :: Python :: 3
Classifier: License :: OSI Approved :: MIT License
Classifier: Operating System :: OS Independent
Requires-Python: >=3.11
Requires-Dist: fastapi~=0.111.0
Requires-Dist: uvicorn~=0.30.1
Requires-Dist: grpcio~=1.68.1
Requires-Dist: grpcio-tools~=1.67.1
Requires-Dist: kubernetes~=31.0.0
Requires-Dist: pydantic~=2.8.2
Requires-Dist: requests~=2.32.3
Requires-Dist: python-dotenv~=1.0.1
Requires-Dist: numpy~=2.0.1
Requires-Dist: jaclang~=0.7.27
